Openix/ChessOpeningsLibrary.py
Openix/Openix.py
Openix/__init__.py
Openix/open/ecoA.json
Openix/open/ecoB.json
Openix/open/ecoC.json
Openix/open/ecoD.json
Openix/open/ecoE.json
openix-2.0.3.dist-info/licenses/LICENSE
openix-2.0.3.dist-info/METADATA
openix-2.0.3.dist-info/WHEEL
openix-2.0.3.dist-info/top_level.txt
openix-2.0.3.dist-info/RECORD
