Metadata-Version: 2.4
Name: Openix
Version: 2.0.3
Summary: A simple chess openings (ECO) library for Python.
Home-page: https://github.com/0xh7/Openix-Library
Author: 0xh7
Author-email: fjdjfjd1424@gmail.com
Keywords: chess,ECO,openings,chess openings,ai chess,python chess,openix,game opening,board games,chess library,python library,python chess library,python chess openings
Classifier: Programming Language :: Python :: 3
Classifier: License :: OSI Approved :: MIT License
Classifier: Operating System :: OS Independent
Requires-Python: >=3.7
License-File: LICENSE
Requires-Dist: python-chess
Dynamic: author
Dynamic: author-email
Dynamic: classifier
Dynamic: home-page
Dynamic: keywords
Dynamic: license-file
Dynamic: requires-dist
Dynamic: requires-python
Dynamic: summary
